NREL_reVRt-0.2.1.dist-info/METADATA
NREL_reVRt-0.2.1.dist-info/WHEEL
NREL_reVRt-0.2.1.dist-info/entry_points.txt
NREL_reVRt-0.2.1.dist-info/licenses/LICENSE
revrt/__init__.py
revrt/_cli.py
revrt/_rust.abi3.so
revrt/constants.py
revrt/costs/__init__.py
revrt/costs/base.py
revrt/costs/cli.py
revrt/costs/config/README.md
revrt/costs/config/__init__.py
revrt/costs/config/base_line_costs.json
revrt/costs/config/config.py
revrt/costs/config/iso_lookup.json
revrt/costs/config/iso_multipliers.json
revrt/costs/config/land_use_classes.json
revrt/costs/config/new_substation_costs.json
revrt/costs/config/power_classes.json
revrt/costs/config/power_to_voltage.json
revrt/costs/config/transformer_costs.json
revrt/costs/config/upgrade_substation_costs.json
revrt/costs/dry_costs_creator.py
revrt/costs/layer_creator.py
revrt/costs/masks.py
revrt/exceptions.py
revrt/models/__init__.py
revrt/models/cost_layers.py
revrt/spatial_characterization/__init__.py
revrt/spatial_characterization/cli.py
revrt/spatial_characterization/stats.py
revrt/spatial_characterization/zonal.py
revrt/utilities/__init__.py
revrt/utilities/base.py
revrt/utilities/cli.py
revrt/utilities/handlers.py
revrt/utilities/raster.py
revrt/warn.py
NREL_reVRt-0.2.1.dist-info/RECORD
